[
  {
    "name": "Adiel Zinio Putra Saragih ",
    "nims": [
      "09021282429113",
      "09021282429114"
    ],
    "nim_counts": {
      "09021282429113": 5,
      "09021282429114": 1
    },
    "total_rows": 6,
    "generated_at": "2025-12-10T11:32:59.607748+00:00"
  },
  {
    "name": "Adyan Faza Elndra",
    "nims": [
      "09021382530164",
      "09021383530164"
    ],
    "nim_counts": {
      "09021382530164": 1,
      "09021383530164": 1
    },
    "total_rows": 2,
    "generated_at": "2025-12-10T11:32:59.607748+00:00"
  },
  {
    "name": "Arkan Syahputra",
    "nims": [
      "09021182429106",
      "09021282419106",
      "09021282429106",
      "090212824292106",
      "090221282429106"
    ],
    "nim_counts": {
      "09021182429106": 1,
      "09021282419106": 1,
      "09021282429106": 28,
      "090212824292106": 1,
      "090221282429106": 1
    },
    "total_rows": 32,
    "generated_at": "2025-12-10T11:32:59.607748+00:00"
  },
  {
    "name": "Azizul Manal Gaumalanga",
    "nims": [
      "009021282429092",
      "09021282429092"
    ],
    "nim_counts": {
      "009021282429092": 1,
      "09021282429092": 24
    },
    "total_rows": 25,
    "generated_at": "2025-12-10T11:32:59.607748+00:00"
  },
  {
    "name": "Fathir Alif",
    "nims": [
      "09021282429112",
      "09021282429113",
      "0902128242911w"
    ],
    "nim_counts": {
      "09021282429112": 23,
      "09021282429113": 1,
      "0902128242911w": 1
    },
    "total_rows": 25,
    "generated_at": "2025-12-10T11:32:59.607748+00:00"
  },
  {
    "name": "Helen Patricia",
    "nims": [
      "09021282419104",
      "09021282429104",
      "0902182429104",
      "09022282429104"
    ],
    "nim_counts": {
      "": 1,
      "09021282419104": 1,
      "09021282429104": 15,
      "0902182429104": 1,
      "09022282429104": 2
    },
    "total_rows": 20,
    "generated_at": "2025-12-10T11:32:59.607748+00:00"
  },
  {
    "name": "Liviya",
    "nims": [
      "00000137371",
      "137371"
    ],
    "nim_counts": {
      "00000137371": 1,
      "137371": 1
    },
    "total_rows": 2,
    "generated_at": "2025-12-10T11:32:59.607748+00:00"
  },
  {
    "name": "Malisyah Nadya Marvini",
    "nims": [
      "03021082429120",
      "03021282429120",
      "09021282429120"
    ],
    "nim_counts": {
      "03021082429120": 1,
      "03021282429120": 2,
      "09021282429120": 18
    },
    "total_rows": 21,
    "generated_at": "2025-12-10T11:32:59.607748+00:00"
  },
  {
    "name": "Malisyah Nadya Marvini ",
    "nims": [
      "09021282429120",
      "090212829120"
    ],
    "nim_counts": {
      "09021282429120": 6,
      "090212829120": 1
    },
    "total_rows": 7,
    "generated_at": "2025-12-10T11:32:59.607748+00:00"
  },
  {
    "name": "Muhammad Iqbal Kurniawan",
    "nims": [
      "090212822429086",
      "09021282429086"
    ],
    "nim_counts": {
      "090212822429086": 2,
      "09021282429086": 22
    },
    "total_rows": 24,
    "generated_at": "2025-12-10T11:32:59.607748+00:00"
  },
  {
    "name": "Muhammad Rofiuddin",
    "nims": [
      "09021282429115",
      "09031282429115"
    ],
    "nim_counts": {
      "09021282429115": 28,
      "09031282429115": 1
    },
    "total_rows": 29,
    "generated_at": "2025-12-10T11:32:59.607748+00:00"
  },
  {
    "name": "Rama Alfira",
    "nims": [
      "09021282429105",
      "09021282429205"
    ],
    "nim_counts": {
      "09021282429105": 21,
      "09021282429205": 1
    },
    "total_rows": 22,
    "generated_at": "2025-12-10T11:32:59.607748+00:00"
  },
  {
    "name": "Rizki Ardiansyah",
    "nims": [
      "0902128242911",
      "09021282429114"
    ],
    "nim_counts": {
      "0902128242911": 1,
      "09021282429114": 22
    },
    "total_rows": 23,
    "generated_at": "2025-12-10T11:32:59.607748+00:00"
  },
  {
    "name": "Wahyu Pratama",
    "nims": [
      "09021282429084",
      "0902182429084"
    ],
    "nim_counts": {
      "09021282429084": 26,
      "0902182429084": 1
    },
    "total_rows": 27,
    "generated_at": "2025-12-10T11:32:59.607748+00:00"
  },
  {
    "name": "cindy nabila shefika",
    "nims": [
      "06131282429060",
      "07131282429060"
    ],
    "nim_counts": {
      "06131282429060": 2,
      "07131282429060": 1
    },
    "total_rows": 3,
    "generated_at": "2025-12-10T11:32:59.607748+00:00"
  }
]